{
    "$id": "properties-directory/structural/magnetic-moments",
    "$schema": "http://json-schema.org/draft-07/schema#",
    "title": "Magnetic moments property schema",
    "description": "magnetization on each ion",
    "type": "object",
    "properties": {
        "name": {
            "enum": [
                "magnetic_moments"
            ]
        },
        "values": {
            "$ref": "../../core/reusable/atomic_vectors.json"
        },
        "units": {
            "$ref": "../../definitions/units.json#/magnetic"
        }
    },
    "required": [
        "name",
        "values",
        "units"
    ]
}
