{
	"cmake" : 
	{
		"generator" : 
		{
			"multiConfig" : false,
			"name" : "Ninja"
		},
		"paths" : 
		{
			"cmake" : "D:/CMake/bin/cmake.exe",
			"cpack" : "D:/CMake/bin/cpack.exe",
			"ctest" : "D:/CMake/bin/ctest.exe",
			"root" : "D:/CMake/share/cmake-4.1"
		},
		"version" : 
		{
			"isDirty" : false,
			"major" : 4,
			"minor" : 1,
			"patch" : 1,
			"string" : "4.1.1",
			"suffix" : ""
		}
	},
	"objects" : 
	[
		{
			"jsonFile" : "codemodel-v2-966359007da491b25b23.json",
			"kind" : "codemodel",
			"version" : 
			{
				"major" : 2,
				"minor" : 8
			}
		},
		{
			"jsonFile" : "cache-v2-09b145ce270b672c71a3.json",
			"kind" : "cache",
			"version" : 
			{
				"major" : 2,
				"minor" : 0
			}
		},
		{
			"jsonFile" : "cmakeFiles-v1-65e730cf80244c8ebc8b.json",
			"kind" : "cmakeFiles",
			"version" : 
			{
				"major" : 1,
				"minor" : 1
			}
		},
		{
			"jsonFile" : "toolchains-v1-88fb38c5eac8230b5f71.json",
			"kind" : "toolchains",
			"version" : 
			{
				"major" : 1,
				"minor" : 0
			}
		}
	],
	"reply" : 
	{
		"cache-v2" : 
		{
			"jsonFile" : "cache-v2-09b145ce270b672c71a3.json",
			"kind" : "cache",
			"version" : 
			{
				"major" : 2,
				"minor" : 0
			}
		},
		"cmakeFiles-v1" : 
		{
			"jsonFile" : "cmakeFiles-v1-65e730cf80244c8ebc8b.json",
			"kind" : "cmakeFiles",
			"version" : 
			{
				"major" : 1,
				"minor" : 1
			}
		},
		"codemodel-v2" : 
		{
			"jsonFile" : "codemodel-v2-966359007da491b25b23.json",
			"kind" : "codemodel",
			"version" : 
			{
				"major" : 2,
				"minor" : 8
			}
		},
		"toolchains-v1" : 
		{
			"jsonFile" : "toolchains-v1-88fb38c5eac8230b5f71.json",
			"kind" : "toolchains",
			"version" : 
			{
				"major" : 1,
				"minor" : 0
			}
		}
	}
}
