[{ "C": "/* vim: set ts={ts} sts={sts} sw={sw} {et} ai si sta: */", "H": "/* vim: set ts={ts} sts={sts} sw={sw} {et} ai si sta: */", "Makefile": "# vim: set ts={ts} sts={sts} sw={sw} {et} ai si sta:", "bash": "# vim: set ts={ts} sts={sts} sw={sw} {et} ai si sta:", "c": "/* vim: set ts={ts} sts={sts} sw={sw} {et} ai si sta: */", "cc": "/* vim: set ts={ts} sts={sts} sw={sw} {et} ai si sta: */", "cpp": "/* vim: set ts={ts} sts={sts} sw={sw} {et} ai si sta: */", "css": "/* vim: set ts={ts} sts={sts} sw={sw} {et} ai si sta: */", "fish": "# vim: set ts={ts} sts={sts} sw={sw} {et} ai si sta:", "h": "/* vim: set ts={ts} sts={sts} sw={sw} {et} ai si sta: */", "hh": "/* vim: set ts={ts} sts={sts} sw={sw} {et} ai si sta: */", "hpp": "/* vim: set ts={ts} sts={sts} sw={sw} {et} ai si sta: */", "htm": "<!-- vim: set ts={ts} sts={sts} sw={sw} {et} ai si sta: -->", "html": "<!-- vim: set ts={ts} sts={sts} sw={sw} {et} ai si sta: -->", "javascript": "/* vim: set ts={ts} sts={sts} sw={sw} {et} ai si sta: */", "javascriptreact": "/* vim: set ts={ts} sts={sts} sw={sw} {et} ai si sta: */", "js": "/* vim: set ts={ts} sts={sts} sw={sw} {et} ai si sta: */", "jsx": "/* vim: set ts={ts} sts={sts} sw={sw} {et} ai si sta: */", "latex": "% vim: set ts={ts} sts={sts} sw={sw} {et} ai si sta:", "lua": "-- vim: set ts={ts} sts={sts} sw={sw} {et} ai si sta:", "make": "# vim: set ts={ts} sts={sts} sw={sw} {et} ai si sta:", "markdown": "<!-- vim: set ts={ts} sts={sts} sw={sw} {et} ai si sta: -->", "md": "<!-- vim: set ts={ts} sts={sts} sw={sw} {et} ai si sta: -->", "mk": "# vim: set ts={ts} sts={sts} sw={sw} {et} ai si sta:", "py": "# vim: set ts={ts} sts={sts} sw={sw} {et} ai si sta:", "pyi": "# vim: set ts={ts} sts={sts} sw={sw} {et} ai si sta:", "python": "# vim: set ts={ts} sts={sts} sw={sw} {et} ai si sta:", "rb": "# vim: set ts={ts} sts={sts} sw={sw} {et} ai si sta:", "rs": "/* vim: set ts={ts} sts={sts} sw={sw} {et} ai si sta: */", "ruby": "# vim: set ts={ts} sts={sts} sw={sw} {et} ai si sta:", "rust": "/* vim: set ts={ts} sts={sts} sw={sw} {et} ai si sta: */", "sh": "# vim: set ts={ts} sts={sts} sw={sw} {et} ai si sta:", "tex": "% vim: set ts={ts} sts={sts} sw={sw} {et} ai si sta:", "toml": "# vim: set ts={ts} sts={sts} sw={sw} {et} ai si sta:", "ts": "/* vim: set ts={ts} sts={sts} sw={sw} {et} ai si sta: */", "tsx": "/* vim: set ts={ts} sts={sts} sw={sw} {et} ai si sta: */", "typescript": "/* vim: set ts={ts} sts={sts} sw={sw} {et} ai si sta: */", "typescriptreact": "/* vim: set ts={ts} sts={sts} sw={sw} {et} ai si sta: */", "xhtml": "<!-- vim: set ts={ts} sts={sts} sw={sw} {et} ai si sta: -->", "xml": "<!-- vim: set ts={ts} sts={sts} sw={sw} {et} ai si sta: -->", "yaml": "# vim: set ts={ts} sts={sts} sw={sw} {et} ai si sta:", "yml": "# vim: set ts={ts} sts={sts} sw={sw} {et} ai si sta:", "zsh": "# vim: set ts={ts} sts={sts} sw={sw} {et} ai si sta:" }, { "C": { "level": 2, "expandtab": true }, "H": { "level": 2, "expandtab": true }, "Makefile": { "level": 4, "expandtab": false }, "bash": { "level": 4, "expandtab": true }, "c": { "level": 2, "expandtab": true }, "cc": { "level": 2, "expandtab": true }, "cpp": { "level": 2, "expandtab": true }, "css": { "level": 4, "expandtab": true }, "fish": { "level": 4, "expandtab": true }, "h": { "level": 2, "expandtab": true }, "hh": { "level": 2, "expandtab": true }, "hpp": { "level": 2, "expandtab": true }, "htm": { "level": 2, "expandtab": true }, "html": { "level": 2, "expandtab": true }, "javascript": { "level": 4, "expandtab": true }, "javascriptreact": { "level": 4, "expandtab": true }, "js": { "level": 4, "expandtab": true }, "jsx": { "level": 4, "expandtab": true }, "latex": { "level": 2, "expandtab": true }, "lua": { "level": 4, "expandtab": true }, "make": { "level": 4, "expandtab": false }, "markdown": { "level": 2, "expandtab": true }, "md": { "level": 2, "expandtab": true }, "mk": { "level": 4, "expandtab": false }, "py": { "level": 4, "expandtab": true }, "pyi": { "level": 4, "expandtab": true }, "python": { "level": 4, "expandtab": true }, "rb": { "level": 2, "expandtab": true }, "rs": { "level": 4, "expandtab": true }, "ruby": { "level": 2, "expandtab": true }, "rust": { "level": 4, "expandtab": true }, "sh": { "level": 4, "expandtab": true }, "tex": { "level": 2, "expandtab": true }, "toml": { "level": 4, "expandtab": true }, "ts": { "level": 4, "expandtab": true }, "tsx": { "level": 4, "expandtab": true }, "typescript": { "level": 4, "expandtab": true }, "typescriptreact": { "level": 4, "expandtab": true }, "xhtml": { "level": 2, "expandtab": true }, "xml": { "level": 2, "expandtab": true }, "yaml": { "level": 2, "expandtab": true }, "yml": { "level": 2, "expandtab": true }, "zsh": { "level": 4, "expandtab": true } }]
