{
    "$id": "properties-directory/non-scalar/stress-tensor",
    "$schema": "http://json-schema.org/draft-07/schema#",
    "title": "Stress tensor property schema",
    "type": "object",

    "properties": {
        "value": {
            "$ref": "../../core/abstract/matrix_3x3.json"
        },
        "name": {
            "enum": [
                "stress_tensor"
            ]
        },
        "units": {
            "$ref": "../../definitions/units.json#/pressure"
        }
    },
    "required": [
        "name",
        "value",
        "units"
    ]
}
