{
    "intel": {
        "tool": "intel",
        "modules": [
            "oneapi/2023.2.0"
        ],
        "platform": "gpp",
        "system": "bsc",
        "type": "cmake",
        "version": "2023.2",
        "build": "cmake-gpp-oneapi-2023.2-i4-cc"
    },
    "gcovr": {
        "tool": "gcovr",
        "modules": [
            "oneapi/2023.2.0",
            "hdf5/1.14.1-2",
            "python/3.12.1-gcc",
            "gcc/13.2.0"
        ],
        "platform": "gpp",
        "system": "bsc",
        "type": "cmake",
        "version": "13.2.0",
        "build": "cmake-gpp-gnu-13.2.0-i4-cc"
    }
}
